odoo/addons/stock_picking_warn_message/README.rst
odoo/addons/stock_picking_warn_message/__init__.py
odoo/addons/stock_picking_warn_message/__manifest__.py
odoo/addons/stock_picking_warn_message/i18n/es.po
odoo/addons/stock_picking_warn_message/i18n/it.po
odoo/addons/stock_picking_warn_message/i18n/pt.po
odoo/addons/stock_picking_warn_message/i18n/pt_BR.po
odoo/addons/stock_picking_warn_message/i18n/stock_picking_warn_message.pot
odoo/addons/stock_picking_warn_message/models/__init__.py
odoo/addons/stock_picking_warn_message/models/stock_picking.py
odoo/addons/stock_picking_warn_message/readme/CONFIGURE.md
odoo/addons/stock_picking_warn_message/readme/CONTRIBUTORS.md
odoo/addons/stock_picking_warn_message/readme/DESCRIPTION.md
odoo/addons/stock_picking_warn_message/readme/USAGE.md
odoo/addons/stock_picking_warn_message/static/description/icon.png
odoo/addons/stock_picking_warn_message/static/description/index.html
odoo/addons/stock_picking_warn_message/tests/__init__.py
odoo/addons/stock_picking_warn_message/tests/test_stock_picking_warn_message.py
odoo/addons/stock_picking_warn_message/views/stock_picking_views.xml
odoo_addon_stock_picking_warn_message-18.0.1.0.0.4.dist-info/METADATA
odoo_addon_stock_picking_warn_message-18.0.1.0.0.4.dist-info/WHEEL
odoo_addon_stock_picking_warn_message-18.0.1.0.0.4.dist-info/top_level.txt
odoo_addon_stock_picking_warn_message-18.0.1.0.0.4.dist-info/RECORD
